jupyblog/__init__.py
jupyblog/ast.py
jupyblog/cli.py
jupyblog/config.py
jupyblog/exceptions.py
jupyblog/execute.py
jupyblog/expand.py
jupyblog/images.py
jupyblog/md.py
jupyblog/medium.py
jupyblog/models.py
jupyblog/postprocess.py
jupyblog/util.py
jupyblog/utm.py
jupyblog-0.0.15.dist-info/LICENSE
jupyblog-0.0.15.dist-info/METADATA
jupyblog-0.0.15.dist-info/WHEEL
jupyblog-0.0.15.dist-info/entry_points.txt
jupyblog-0.0.15.dist-info/top_level.txt
jupyblog-0.0.15.dist-info/RECORD
