Metadata-Version: 2.1
Name: jupyblog
Version: 0.0.15
License-File: LICENSE
Requires-Dist: pyyaml
Requires-Dist: jinja2
Requires-Dist: jupyter_client
Requires-Dist: ipykernel
Requires-Dist: click
Requires-Dist: jupytext
Requires-Dist: parso
Requires-Dist: pydantic
Requires-Dist: mistune<3,>=2.0
Requires-Dist: ploomber-core>=0.0.4
Requires-Dist: nbformat
Provides-Extra: all
Requires-Dist: ghapi; extra == "all"
Provides-Extra: dev
Requires-Dist: pkgmt; extra == "dev"
Requires-Dist: pytest; extra == "dev"
Requires-Dist: yapf; extra == "dev"
Requires-Dist: flake8; extra == "dev"
Requires-Dist: invoke; extra == "dev"
Requires-Dist: twine; extra == "dev"
Requires-Dist: ipdb; extra == "dev"
Requires-Dist: matplotlib; extra == "dev"
Requires-Dist: pandas; extra == "dev"
Requires-Dist: ploomber-engine; extra == "dev"
Requires-Dist: ghapi; extra == "dev"
